Metadata-Version: 1.1
Name: starchart
Version: 0.3.1
Summary: Starlette's api document support
Home-page: https://github.com/strongbugman/starchart
Author: Bruce Wu
Author-email: strongbugman@gmail.com
License: BSD
Platform: UNKNOWN
Classifier: Environment :: Console
Classifier: Programming Language :: Python :: 3.6
Classifier: Programming Language :: Python :: 3.7
Classifier: Topic :: Internet :: WWW/HTTP
Classifier: Topic :: Software Development :: Libraries :: Application Frameworks
Classifier: Topic :: Software Development :: Libraries :: Python Modules
